{
    "dom": {
        "username": "DomC18",
        "password": "fortnite"
    },
    "tasks": [
        {
            "name": "pluh",
            "description": "short task",
            "deadline": "tomorrow",
            "status": 2,
            "importance": 3
        },
        {
            "name": "no",
            "description": "short task",
            "deadline": "tomorrow",
            "status": 2,
            "importance": 3
        },
        {
            "name": "hi",
            "description": "short task",
            "deadline": "tomorrow",
            "status": 2,
            "importance": 3
        },
        {
            "name": "hello",
            "description": "short task",
            "deadline": "tomorrow",
            "status": 2,
            "importance": 3
        },
        {
            "name": "looey",
            "description": "short task",
            "deadline": "tomorrow",
            "status": 2,
            "importance": 3
        },
        {
            "name": "dooky",
            "description": "short task",
            "deadline": "tomorrow",
            "status": 2,
            "importance": 3
        },
        {
            "name": "poop",
            "description": "short task",
            "deadline": "tomorrow",
            "status": 2,
            "importance": 3
        },
        {
            "name": "pluh",
            "description": "short task",
            "deadline": "tomorrow",
            "status": 2,
            "importance": 3
        },
        {
            "name": "no",
            "description": "short task",
            "deadline": "tomorrow",
            "status": 2,
            "importance": 3
        }
    ]
}